{
"44.1459,12.2379": {
"alt": 37,
"minuti": 28
},
"44.2316,12.0054": {
"alt": 30,
"minuti": 9
},
"44.2261,12.0563": {
"alt": 25,
"minuti": 4
},
"44.1401,12.2605": {
"alt": 32,
"minuti": 25
},
"44.1897,12.1309": {
"alt": 29,
"minuti": 13
},
"44.1066,12.4163": {
"alt": 22,
"minuti": 34
},
"44.258,12.0268": {
"alt": 22,
"minuti": 11
},
"44.1437,12.2437": {
"alt": 40,
"minuti": 26
},
"44.234,12.0199": {
"alt": 28,
"minuti": 6
},
"44.1823,12.424": {
"alt": 3,
"minuti": 41
},
"44.2153,12.0478": {
"alt": 31,
"minuti": 4
},
"44.2254,12.0367": {
"alt": 34,
"minuti": 2
},
"44.2197,12.0599": {
"alt": 26,
"minuti": 4
},
"44.1989,12.4066": {
"alt": 4,
"minuti": 41
},
"44.1707,12.4268": {
"alt": 3,
"minuti": 38
},
"44.1391,12.2373": {
"alt": 38,
"minuti": 27
},
"44.1499,12.2583": {
"alt": 32,
"minuti": 25
},
"44.0464,12.0124": {
"alt": 112,
"minuti": 25
},
"44.1414,12.2451": {
"alt": 44,
"minuti": 27
},
"44.1416,12.2452": {
"alt": 44,
"minuti": 27
},
"44.141,12.2455": {
"alt": 44,
"minuti": 27
},
"44.1928,12.4092": {
"alt": 6,
"minuti": 41
},
"44.0848,12.1085": {
"alt": 325,
"minuti": 28
},
"44.162,12.177": {
"alt": 33,
"minuti": 19
},
"44.1909,12.033": {
"alt": 45,
"minuti": 7
},
"44.1353,12.2436": {
"alt": 48,
"minuti": 28
},
"44.1784,12.4222": {
"alt": 3,
"minuti": 41
},
"44.2246,12.0371": {
"alt": 37,
"minuti": 3
},
"44.1605,12.2691": {
"alt": 26,
"minuti": 23
},
"44.2231,12.0325": {
"alt": 35,
"minuti": 4
},
"44.1566,12.2609": {
"alt": 30,
"minuti": 25
},
"44.2261,12.0448": {
"alt": 30,
"minuti": 4
},
"44.1617,12.1505": {
"alt": 53,
"minuti": 18
},
"44.2232,12.1124": {
"alt": 23,
"minuti": 13
},
"44.189,12.126": {
"alt": 33,
"minuti": 13
},
"44.2017,12.0424": {
"alt": 35,
"minuti": 7
},
"44.2229,12.0202": {
"alt": 31,
"minuti": 6
},
"44.0839,12.1102": {
"alt": 269,
"minuti": 31
},
"44.1619,12.1756": {
"alt": 32,
"minuti": 21
},
"44.2121,12.0836": {
"alt": 23,
"minuti": 8
},
"44.1918,12.0354": {
"alt": 42,
"minuti": 8
},
"44.1221,11.887": {
"alt": 136,
"minuti": 21
},
"44.1472,12.3112": {
"alt": 21,
"minuti": 28
},
"44.0427,12.318": {
"alt": 287,
"minuti": 46
},
"44.1215,12.3443": {
"alt": 25,
"minuti": 36
},
"44.0334,12.3657": {
"alt": 238,
"minuti": 42
},
"44.0207,11.9715": {
"alt": 186,
"minuti": 29
},
"44.2028,12.0589": {
"alt": 28,
"minuti": 7
},
"44.2046,12.0311": {
"alt": 39,
"minuti": 6
},
"44.0062,11.9422": {
"alt": 221,
"minuti": 32
},
"44.139,12.243": {
"alt": 47,
"minuti": 28
},
"44.222,12.041": {
"alt": 33,
"minuti": 1
},
"44.101,11.982": {
"alt": 137,
"minuti": 21
},
"44.127,12.061": {
"alt": 64,
"minuti": 17
},
"44.148,12.135": {
"alt": 220,
"minuti": 19
},
"44.174,11.941": {
"alt": 155,
"minuti": 20
},
"44.121,11.885": {
"alt": 127,
"minuti": 21
},
"44.108,12.417": {
"alt": 20,
"minuti": 33
},
"43.959,12.196": {
"alt": 159,
"minuti": 43
},
"44.1632,12.176": {
"alt": 35,
"minuti": 20
},
"44.1812,12.2006": {
"alt": 27,
"minuti": 24
},
"44.0383,12.0572": {
"alt": 362,
"minuti": 36
},
"44.1814,12.0324": {
"alt": 50,
"minuti": 8
},
"44.1507,12.3838": {
"alt": 9,
"minuti": 34
},
"44.0826,12.3048": {
"alt": 160,
"minuti": 36
},
"44.1585,12.0398": {
"alt": 111,
"minuti": 13
},
"44.2374,12.0019": {
"alt": 29,
"minuti": 8
},
"44.2329,12.0113": {
"alt": 30,
"minuti": 8
},
"44.2108,12.0483": {
"alt": 33,
"minuti": 5
},
"44.2302,12.0372": {
"alt": 29,
"minuti": 4
},
"44.1078,12.4159": {
"alt": 19,
"minuti": 33
},
"44.2158,11.9811": {
"alt": 43,
"minuti": 13
},
"44.1603,12.3477": {
"alt": 12,
"minuti": 32
},
"44.0203,11.9726": {
"alt": 192,
"minuti": 29
},
"44.2345,12.0324": {
"alt": 26,
"minuti": 5
},
"44.0853,12.0545": {
"alt": 105,
"minuti": 22
},
"44.1164,12.0001": {
"alt": 379,
"minuti": 23
},
"44.1568,12.3939": {
"alt": 5,
"minuti": 36
},
"44.0465,12.012": {
"alt": 112,
"minuti": 25
},
"44.1575,12.27": {
"alt": 27,
"minuti": 23
},
"44.1724,12.1595": {
"alt": 29,
"minuti": 16
},
"44.1645,12.1747": {
"alt": 35,
"minuti": 19
},
"44.1799,12.1661": {
"alt": 27,
"minuti": 19
},
"44.1648,12.1762": {
"alt": 33,
"minuti": 19
},
"44.1505,12.1369": {
"alt": 181,
"minuti": 18
},
"44.2011,12.1865": {
"alt": 22,
"minuti": 22
},
"44.1503,12.1385": {
"alt": 172,
"minuti": 19
},
"44.1955,12.1856": {
"alt": 25,
"minuti": 21
},
"44.1683,12.1273": {
"alt": 52,
"minuti": 15
},
"44.1615,12.1496": {
"alt": 51,
"minuti": 18
},
"44.1475,12.1244": {
"alt": 81,
"minuti": 22
},
"44.1484,12.1335": {
"alt": 246,
"minuti": 21
},
"44.1487,12.1366": {
"alt": 193,
"minuti": 19
},
"44.1482,12.1365": {
"alt": 195,
"minuti": 19
},
"44.1298,12.1248": {
"alt": 205,
"minuti": 24
},
"44.1474,12.1348": {
"alt": 253,
"minuti": 19
},
"44.1503,12.1321": {
"alt": 205,
"minuti": 20
},
"44.2196,12.2089": {
"alt": 17,
"minuti": 23
},
"44.1457,12.1027": {
"alt": 53,
"minuti": 19
},
"44.1639,12.1527": {
"alt": 56,
"minuti": 18
},
"44.1453,12.1392": {
"alt": 196,
"minuti": 20
},
"44.1992,12.1867": {
"alt": 24,
"minuti": 22
},
"44.2031,12.1703": {
"alt": 21,
"minuti": 21
},
"44.1711,12.1598": {
"alt": 29,
"minuti": 16
},
"44.1435,12.099": {
"alt": 52,
"minuti": 19
},
"44.1706,12.1563": {
"alt": 28,
"minuti": 17
},
"44.1509,12.1328": {
"alt": 169,
"minuti": 18
},
"44.1503,12.1595": {
"alt": 51,
"minuti": 22
},
"44.1419,12.0979": {
"alt": 60,
"minuti": 20
},
"44.1389,12.1002": {
"alt": 51,
"minuti": 22
},
"44.1434,12.0999": {
"alt": 49,
"minuti": 19
},
"44.1482,12.1343": {
"alt": 252,
"minuti": 21
},
"44.1512,12.1375": {
"alt": 172,
"minuti": 18
},
"44.1496,12.135": {
"alt": 185,
"minuti": 19
},
"44.2007,12.1877": {
"alt": 24,
"minuti": 22
},
"44.1503,12.113": {
"alt": 156,
"minuti": 19
},
"44.2025,12.1899": {
"alt": 24,
"minuti": 22
},
"44.143,12.1422": {
"alt": 216,
"minuti": 21
},
"44.1507,12.136": {
"alt": 175,
"minuti": 18
},
"44.146,12.1366": {
"alt": 205,
"minuti": 19
},
"44.1511,12.1391": {
"alt": 174,
"minuti": 19
},
"44.1405,12.1005": {
"alt": 52,
"minuti": 19
},
"44.1521,12.1014": {
"alt": 44,
"minuti": 18
},
"44.1704,12.1577": {
"alt": 30,
"minuti": 17
},
"44.1702,12.1599": {
"alt": 30,
"minuti": 16
},
"44.1713,12.1274": {
"alt": 35,
"minuti": 15
},
"44.1436,12.1427": {
"alt": 185,
"minuti": 21
},
"44.1492,12.1337": {
"alt": 209,
"minuti": 20
},
"44.188,12.127": {
"alt": 34,
"minuti": 13
},
"44.1742,12.2138": {
"alt": 27,
"minuti": 21
},
"44.1392,12.2497": {
"alt": 42,
"minuti": 27
},
"44.1382,12.2372": {
"alt": 38,
"minuti": 27
},
"44.1315,12.2303": {
"alt": 36,
"minuti": 28
},
"44.1802,12.1993": {
"alt": 28,
"minuti": 23
},
"44.1517,12.2527": {
"alt": 34,
"minuti": 25
},
"44.157,12.2391": {
"alt": 25,
"minuti": 26
},
"44.1554,12.2398": {
"alt": 27,
"minuti": 26
},
"44.1483,12.2203": {
"alt": 34,
"minuti": 26
},
"44.1322,12.2479": {
"alt": 45,
"minuti": 28
},
"44.1413,12.252": {
"alt": 40,
"minuti": 26
},
"44.1491,12.2496": {
"alt": 35,
"minuti": 27
},
"44.1825,12.2": {
"alt": 27,
"minuti": 24
},
"44.173,12.2143": {
"alt": 27,
"minuti": 22
},
"44.0424,12.2191": {
"alt": 391,
"minuti": 41
},
"44.1384,12.2366": {
"alt": 33,
"minuti": 27
},
"44.1393,12.2431": {
"alt": 44,
"minuti": 28
},
"44.1353,12.244": {
"alt": 48,
"minuti": 28
},
"44.1433,12.2402": {
"alt": 37,
"minuti": 27
},
"44.1385,12.2445": {
"alt": 46,
"minuti": 28
},
"44.1821,12.2024": {
"alt": 27,
"minuti": 22
},
"44.1907,12.2694": {
"alt": 16,
"minuti": 25
},
"44.0987,12.2427": {
"alt": 184,
"minuti": 36
},
"44.148,12.2372": {
"alt": 35,
"minuti": 29
},
"44.17,12.3049": {
"alt": 16,
"minuti": 24
},
"44.1373,12.2652": {
"alt": 34,
"minuti": 27
},
"44.0527,12.1767": {
"alt": 82,
"minuti": 33
},
"44.1509,12.2495": {
"alt": 33,
"minuti": 26
},
"44.1383,12.2419": {
"alt": 45,
"minuti": 28
},
"44.1514,12.2637": {
"alt": 31,
"minuti": 24
},
"44.0769,12.1579": {
"alt": 283,
"minuti": 34
},
"44.1411,12.2435": {
"alt": 42,
"minuti": 27
},
"44.1422,12.2301": {
"alt": 30,
"minuti": 26
},
"44.1377,12.2314": {
"alt": 32,
"minuti": 27
},
"44.1267,12.2423": {
"alt": 53,
"minuti": 30
},
"44.1399,12.2426": {
"alt": 44,
"minuti": 28
},
"44.1749,12.2145": {
"alt": 29,
"minuti": 21
},
"44.1411,12.2485": {
"alt": 42,
"minuti": 26
},
"44.2,12.395": {
"alt": 4,
"minuti": 39
},
"44.11,12.388": {
"alt": 19,
"minuti": 29
},
"44.09,12.395": {
"alt": 37,
"minuti": 33
},
"44.121,12.339": {
"alt": 26,
"minuti": 35
},
"43.997,11.913": {
"alt": 235,
"minuti": 35
},
"44.06,11.845": {
"alt": 211,
"minuti": 28
},
"44.1106,12.3398": {
"alt": 30,
"minuti": 34
},
"44.1178,12.3271": {
"alt": 31,
"minuti": 34
},
"44.1123,12.341": {
"alt": 28,
"minuti": 34
},
"44.1087,12.3402": {
"alt": 31,
"minuti": 34
},
"44.1107,12.3365": {
"alt": 32,
"minuti": 34
},
"44.1107,12.3547": {
"alt": 22,
"minuti": 32
},
"44.1134,12.3436": {
"alt": 27,
"minuti": 34
},
"44.1215,12.341": {
"alt": 26,
"minuti": 35
},
"44.1164,12.343": {
"alt": 27,
"minuti": 34
},
"44.1164,12.348": {
"alt": 24,
"minuti": 34
},
"44.1108,12.3619": {
"alt": 23,
"minuti": 31
},
"44.1202,12.328": {
"alt": 28,
"minuti": 34
},
"44.1083,12.3371": {
"alt": 34,
"minuti": 33
},
"44.1241,12.3392": {
"alt": 24,
"minuti": 35
},
"44.1216,12.3442": {
"alt": 25,
"minuti": 36
},
"44.1203,12.3426": {
"alt": 26,
"minuti": 36
},
"44.1097,12.3378": {
"alt": 31,
"minuti": 34
},
"44.1187,12.34": {
"alt": 27,
"minuti": 35
},
"44.118,12.3399": {
"alt": 28,
"minuti": 35
},
"44.1213,12.3441": {
"alt": 25,
"minuti": 36
},
"44.1153,12.3267": {
"alt": 34,
"minuti": 34
},
"44.1164,12.3383": {
"alt": 28,
"minuti": 36
},
"44.1086,12.3382": {
"alt": 32,
"minuti": 33
},
"44.1088,12.3386": {
"alt": 31,
"minuti": 34
},
"44.1169,12.3325": {
"alt": 30,
"minuti": 35
},
"44.1193,12.3404": {
"alt": 27,
"minuti": 36
},
"44.1086,12.3383": {
"alt": 32,
"minuti": 33
},
"44.1053,12.3343": {
"alt": 37,
"minuti": 33
},
"44.1166,12.3452": {
"alt": 28,
"minuti": 35
},
"44.119,12.3376": {
"alt": 27,
"minuti": 36
},
"44.1234,12.3394": {
"alt": 24,
"minuti": 35
},
"44.1099,12.34": {
"alt": 31,
"minuti": 34
},
"44.1136,12.3273": {
"alt": 32,
"minuti": 34
},
"44.1182,12.3388": {
"alt": 29,
"minuti": 35
},
"44.2098,12.0329": {
"alt": 37,
"minuti": 4
},
"44.2182,12.0586": {
"alt": 27,
"minuti": 4
},
"44.204,12.0581": {
"alt": 29,
"minuti": 7
},
"44.2486,12.0384": {
"alt": 23,
"minuti": 9
},
"44.2071,12.046": {
"alt": 32,
"minuti": 5
},
"44.1486,12.0791": {
"alt": 46,
"minuti": 14
},
"44.1563,12.0403": {
"alt": 110,
"minuti": 16
},
"44.2214,12.0516": {
"alt": 29,
"minuti": 3
},
"44.2044,12.0349": {
"alt": 36,
"minuti": 6
},
"44.2136,12.0528": {
"alt": 29,
"minuti": 4
},
"44.2349,12.0316": {
"alt": 27,
"minuti": 5
},
"44.2378,12.033": {
"alt": 26,
"minuti": 5
},
"44.2369,12.0017": {
"alt": 29,
"minuti": 8
},
"44.2261,12.0352": {
"alt": 33,
"minuti": 3
},
"44.1948,12.0309": {
"alt": 44,
"minuti": 6
},
"44.2073,12.0593": {
"alt": 25,
"minuti": 5
},
"44.2181,12.0561": {
"alt": 29,
"minuti": 4
},
"44.2251,12.0416": {
"alt": 36,
"minuti": 4
},
"44.2124,12.0442": {
"alt": 32,
"minuti": 4
},
"44.2205,12.0254": {
"alt": 31,
"minuti": 6
},
"44.2234,12.0426": {
"alt": 37,
"minuti": 4
},
"44.211,12.0539": {
"alt": 29,
"minuti": 4
},
"44.2115,12.0348": {
"alt": 37,
"minuti": 4
},
"44.2058,12.0289": {
"alt": 36,
"minuti": 5
},
"44.2085,12.0308": {
"alt": 36,
"minuti": 5
},
"44.2103,12.0366": {
"alt": 35,
"minuti": 5
},
"44.2081,12.0321": {
"alt": 37,
"minuti": 5
},
"44.1619,12.1762": {
"alt": 33,
"minuti": 20
},
"44.1811,12.0314": {
"alt": 49,
"minuti": 8
},
"44.1818,12.2018": {
"alt": 27,
"minuti": 22
},
"44.1493,12.3825": {
"alt": 10,
"minuti": 34
},
"43.795,12.006": {
"alt": 827,
"minuti": 72
},
"44.031,12.353": {
"alt": 255,
"minuti": 44
},
"43.831,11.958": {
"alt": 498,
"minuti": 66
},
"44.2373,12.0271": {
"alt": 27,
"minuti": 5
},
"44.0798,12.3016": {
"alt": 169,
"minuti": 38
},
"44.1551,11.7865": {
"alt": 240,
"minuti": 40
},
"44.158,12.0392": {
"alt": 116,
"minuti": 13
},
"44.2109,12.0483": {
"alt": 31,
"minuti": 5
},
"44.2255,12.0316": {
"alt": 35,
"minuti": 4
},
"44.1872,11.9606": {
"alt": 60,
"minuti": 13
},
"44.0871,12.1109": {
"alt": 268,
"minuti": 29
},
"44.1616,12.1749": {
"alt": 33,
"minuti": 21
},
"44.1926,12.0314": {
"alt": 45,
"minuti": 6
},
"44.0863,12.1113": {
"alt": 264,
"minuti": 30
},
"44.1621,12.1747": {
"alt": 32,
"minuti": 19
},
"44.1926,12.0336": {
"alt": 42,
"minuti": 7
},
"44.006,11.938": {
"alt": 221,
"minuti": 34
},
"44.0517,12.1768": {
"alt": 73,
"minuti": 33
},
"44.1831,12.2003": {
"alt": 27,
"minuti": 22
},
"44.1797,12.2019": {
"alt": 28,
"minuti": 22
},
"44.1468,12.0774": {
"alt": 46,
"minuti": 14
},
"44.1592,12.0387": {
"alt": 105,
"minuti": 13
}
}